mfsapi/__init__.py
mfsapi/api.py
mfsapi/client.py
mfsapi/config.py
mfsapi/server.py
mfsapi-0.1.2.dist-info/METADATA
mfsapi-0.1.2.dist-info/WHEEL
mfsapi-0.1.2.dist-info/top_level.txt
mfsapi-0.1.2.dist-info/RECORD
