Metadata-Version: 2.4
Name: mfsapi
Version: 0.1.2
Summary: SSAPI — Fully free and extensible server/client skeleton
Author: maksalmaz
License: MIT
Classifier: Programming Language :: Python :: 3
Classifier: License :: OSI Approved :: MIT License
Classifier: Operating System :: OS Independent
Requires-Python: >=3.8
Dynamic: author
Dynamic: classifier
Dynamic: description
Dynamic: description-content-type
Dynamic: license
Dynamic: requires-python
Dynamic: summary
